scalasparrk/__init__.py
scalasparrk/prac1.py
scalasparrk/prac3.py
scalasparrk/prac4.py
scalasparrk/prac5.py
scalasparrk/prac6.py
scalasparrk-0.1.4.dist-info/licenses/LICENSE
scalasparrk-0.1.4.dist-info/METADATA
scalasparrk-0.1.4.dist-info/WHEEL
scalasparrk-0.1.4.dist-info/top_level.txt
scalasparrk-0.1.4.dist-info/RECORD
