Metadata-Version: 2.4
Name: scalasparrk
Version: 0.1.4
Summary: A simple scala spark practice package with practicals (prac1–prac6).
Author: Enzo Martini
Author-email: Enzo Martini <enzomartini.1995@gmail.com>
License: MIT License
Project-URL: Homepage, https://github.com/enzomartini1995-del/scalasparrk
Project-URL: Bug Tracker, https://github.com/enzomartini1995-del/scalasparrk
Requires-Python: >=3.6
License-File: LICENSE
Dynamic: author
Dynamic: license-file
Dynamic: requires-python
